{"class_name": "Trigonella Foenum-graecum (Kelabat)", "name": "Kelabat", "desc": "Klabet atau Fenugreek merupakan tumbuhan dari keluarga Fabaceae. Klabet dapat digunakan untuk obat herbal herb dan sebagai rempah, dikenal juga dengan nama methi. Tumbuhan ini dibudidayakan secara global sebagai semi-arid crop dan merupakan bumbu umum untuk pembuatan kari atau kare.", "scientific_name": "Trigonella foenum-graecum", "img_urls": ["http://www.tanobat.com/wp-content/uploads/fenugreek-plant.jpg", "https://rubi77botani.files.wordpress.com/2017/11/7b345-methichutneyimagecopyrighted3.jpg?w=640"]}